MANIFEST.in
README.rst
setup.py
Flask_Obscurity.egg-info/PKG-INFO
Flask_Obscurity.egg-info/SOURCES.txt
Flask_Obscurity.egg-info/dependency_links.txt
Flask_Obscurity.egg-info/not-zip-safe
Flask_Obscurity.egg-info/requires.txt
Flask_Obscurity.egg-info/top_level.txt
flask_obscurity/__init__.py
flask_obscurity/static/js/uoe.js