Metadata-Version: 1.1
Name: Flask-Obscurity
Version: 0.4
Summary: Security-by-obscurity. Move along, nothing to see here.
Home-page: http://github.com/mbr/flask-obscurity
Author: Marc Brinkmann
Author-email: git@marcbrinkmann.de
License: BSD
Platform: any
Classifier: Environment :: Web Environment
Classifier: Intended Audience :: Developers
Classifier: License :: OSI Approved :: BSD License
Classifier: Operating System :: OS Independent
Classifier: Programming Language :: Python
Classifier: Topic :: Internet :: WWW/HTTP :: Dynamic Content
Classifier: Topic :: Software Development :: Libraries :: Python Modules
